{
    "One Piece": [
        {
            "episode": "54"
        },
        {
            "episode": "55"
        },
        {
            "episode": "56"
        },
        {
            "episode": "57"
        },
        {
            "episode": "58"
        },
        {
            "episode": "59"
        },
        {
            "episode": "60"
        },
        {
            "episode": "61"
        },
        {
            "episode": "98"
        },
        {
            "episode": "99"
        },
        {
            "episode": "101"
        },
        {
            "episode": "102"
        },
        {
            "episode": "131"
        },
        {
            "episode": "132"
        },
        {
            "episode": "133"
        },
        {
            "episode": "134"
        },
        {
            "episode": "135"
        },
        {
            "episode": "136"
        },
        {
            "episode": "137"
        },
        {
            "episode": "138"
        },
        {
            "episode": "139"
        },
        {
            "episode": "140"
        },
        {
            "episode": "141"
        },
        {
            "episode": "142"
        },
        {
            "episode": "143"
        },
        {
            "episode": "196"
        },
        {
            "episode": "197"
        },
        {
            "episode": "198"
        },
        {
            "episode": "199"
        },
        {
            "episode": "200"
        },
        {
            "episode": "201"
        },
        {
            "episode": "202"
        },
        {
            "episode": "203"
        },
        {
            "episode": "204"
        },
        {
            "episode": "205"
        },
        {
            "episode": "206"
        },
        {
            "episode": "220"
        },
        {
            "episode": "221"
        },
        {
            "episode": "222"
        },
        {
            "episode": "223"
        },
        {
            "episode": "224"
        },
        {
            "episode": "225"
        },
        {
            "episode": "226"
        },
        {
            "episode": "279"
        },
        {
            "episode": "280"
        },
        {
            "episode": "281"
        },
        {
            "episode": "282"
        },
        {
            "episode": "283"
        },
        {
            "episode": "291"
        },
        {
            "episode": "292"
        },
        {
            "episode": "303"
        },
        {
            "episode": "317"
        },
        {
            "episode": "318"
        },
        {
            "episode": "319"
        },
        {
            "episode": "326"
        },
        {
            "episode": "327"
        },
        {
            "episode": "328"
        },
        {
            "episode": "329"
        },
        {
            "episode": "330"
        },
        {
            "episode": "331"
        },
        {
            "episode": "332"
        },
        {
            "episode": "333"
        },
        {
            "episode": "334"
        },
        {
            "episode": "335"
        },
        {
            "episode": "336"
        },
        {
            "episode": "382"
        },
        {
            "episode": "383"
        },
        {
            "episode": "384"
        },
        {
            "episode": "406"
        },
        {
            "episode": "407"
        },
        {
            "episode": "426"
        },
        {
            "episode": "427"
        },
        {
            "episode": "428"
        },
        {
            "episode": "429"
        },
        {
            "episode": "457"
        },
        {
            "episode": "458"
        },
        {
            "episode": "492"
        },
        {
            "episode": "542"
        },
        {
            "episode": "575"
        },
        {
            "episode": "576"
        },
        {
            "episode": "577"
        },
        {
            "episode": "578"
        },
        {
            "episode": "590"
        },
        {
            "episode": "626"
        },
        {
            "episode": "627"
        },
        {
            "episode": "628"
        },
        {
            "episode": "747"
        },
        {
            "episode": "748"
        },
        {
            "episode": "749"
        },
        {
            "episode": "750"
        },
        {
            "episode": "775"
        },
        {
            "episode": "780"
        },
        {
            "episode": "781"
        },
        {
            "episode": "782"
        },
        {
            "episode": "807"
        },
        {
            "episode": "881"
        },
        {
            "episode": "895"
        },
        {
            "episode": "896"
        },
        {
            "episode": "907"
        }
    ]
}
